lhs_mcp_demo_lh/__init__.py
lhs_mcp_demo_lh-0.1.0.dist-info/WHEEL
lhs_mcp_demo_lh-0.1.0.dist-info/entry_points.txt
lhs_mcp_demo_lh-0.1.0.dist-info/METADATA
lhs_mcp_demo_lh-0.1.0.dist-info/RECORD
